hacktegic/__main__.py
hacktegic/_internal/base_command.py
hacktegic/_internal/config.py
hacktegic/_internal/credentials.py
hacktegic/_internal/parser.py
hacktegic/_internal/commands/auth/login.py
hacktegic/_internal/commands/auth/logout.py
hacktegic/_internal/commands/auth/register.py
hacktegic/_internal/commands/config/get.py
hacktegic/_internal/commands/config/set.py
hacktegic/_internal/commands/networks/create.py
hacktegic/_internal/commands/networks/delete.py
hacktegic/_internal/commands/networks/describe.py
hacktegic/_internal/commands/networks/list.py
hacktegic/_internal/commands/networks/update.py
hacktegic/_internal/commands/projects/create.py
hacktegic/_internal/commands/projects/delete.py
hacktegic/_internal/commands/projects/describe.py
hacktegic/_internal/commands/projects/list.py
hacktegic/_internal/commands/projects/update.py
hacktegic/_internal/commands/scanprofiles/create.py
hacktegic/_internal/commands/scanprofiles/delete.py
hacktegic/_internal/commands/scanprofiles/describe.py
hacktegic/_internal/commands/scanprofiles/list.py
hacktegic/_internal/commands/scanprofiles/networks_attach.py
hacktegic/_internal/commands/scanprofiles/networks_detach.py
hacktegic/_internal/commands/scanprofiles/networks_list.py
hacktegic/_internal/commands/scanprofiles/portscans_run.py
hacktegic/_internal/commands/scanprofiles/update.py
hacktegic/_internal/commands/scans/delete.py
hacktegic/_internal/commands/scans/describe.py
hacktegic/_internal/commands/scans/list.py
hacktegic/cloud/api_clients/networks.py
hacktegic/cloud/api_clients/projects.py
hacktegic/cloud/api_clients/scanprofiles.py
hacktegic/cloud/api_clients/scans.py
hacktegic/cloud/resources/networks.py
hacktegic/cloud/resources/projects.py
hacktegic/cloud/resources/scanprofiles.py
hacktegic/cloud/resources/scans.py
hacktegic-0.2.0.dist-info/METADATA
hacktegic-0.2.0.dist-info/WHEEL
hacktegic-0.2.0.dist-info/entry_points.txt
hacktegic-0.2.0.dist-info/licenses/LICENSE
hacktegic-0.2.0.dist-info/RECORD
