Metadata-Version: 2.3
Name: hacktegic
Version: 0.2.0
Summary: Hacktegic CLI
Project-URL: Homepage, https://github.com/hacktegic/cli
Project-URL: Bug Tracker, https://github.com/hacktegic/cli/issues
Project-URL: Release Notes, https://github.com/hacktegic/cli/releases
Author-email: Artiom Mocrenco <artiomm@hacktegic.com>
License-File: LICENSE
Classifier: Development Status :: 2 - Pre-Alpha
Classifier: Environment :: Console
Classifier: License :: Other/Proprietary License
Classifier: Programming Language :: Python :: 3
Classifier: Topic :: Security
Requires-Python: >=3.12
Requires-Dist: aiofiles~=23.2.1
Requires-Dist: aiohttp~=3.9.0b1
Requires-Dist: platformdirs<4.3,>=3.11
Requires-Dist: pydantic<2.8,>=2.5
Requires-Dist: requests~=2.31.0
Requires-Dist: rich<13.8,>=13.6
Requires-Dist: tomlkit~=0.12.2
